business_theme/__init__.py
business_theme/__main__.py
business_theme/back_cover.html
business_theme/cover.html
business_theme/layout.html
business_theme/page.html
business_theme/theme.conf
business_theme/static/fonts/FiraSans-Bold.otf
business_theme/static/fonts/FiraSans-Italic.otf
business_theme/static/fonts/FiraSans-Light.otf
business_theme/static/fonts/FiraSans-LightItalic.otf
business_theme/static/fonts/FiraSans-Regular.otf
business_theme/static/fonts/fa-solid-900.eot
business_theme/static/fonts/fa-solid-900.svg
business_theme/static/fonts/fa-solid-900.ttf
business_theme/static/fonts/fa-solid-900.woff
business_theme/static/fonts/fa-solid-900.woff2
business_theme/static/images/cover-bg.png
business_theme/static/styles/main.css
sphinx_business_theme-0.1.0.dist-info/AUTHORS.rst
sphinx_business_theme-0.1.0.dist-info/METADATA
sphinx_business_theme-0.1.0.dist-info/WHEEL
sphinx_business_theme-0.1.0.dist-info/entry_points.txt
sphinx_business_theme-0.1.0.dist-info/top_level.txt
sphinx_business_theme-0.1.0.dist-info/RECORD
